{"geometry": "1800x1098+5+39", "layout_mode": "maze", "maze_difficulty": "hard", "mv_route_planning_mode_enable": false, "mv_routing_deprecated": 1, "machine_vision_master_enable": true, "fast_mode_enabled": true, "long_run_mode_enabled": false, "challenge_mode_enabled": false, "kernel_phase_disabled": [], "kernel_phase_autostep_enable": true, "kernel_phase_observation_floor_override": null, "kernel_phase_program_state": {"phase_set_signature": "phase_mvt0_instrumentation_and_gate_reliability[mvt0.m1_preflight_parser_hardening,mvt0.m2_intervention_taxonomy_lock,mvt0.m3_reasoning_conf_signal_enable]||phase_mvt1_mv_to_learned_routing_bias_lift[mvt1.m1_mv_prior_weight_rebalance,mvt1.m2_mv_disagreement_dynamic_relief,mvt1.m3_objective_evidence_quality_gate]||phase_mvt2_intervention_rate_compression_soft_first[mvt2.m1_soft_substitution_before_override,mvt2.m2_override_budget_strictness_tuning,mvt2.m3_unresolved_context_override_guard]||phase_mvt3_memory_driven_learned_selection_lift[mvt3.m1_cause_effect_priority_lift,mvt3.m2_stm_to_semantic_promotion_quality_tuning,mvt3.m3_pattern_uncertainty_feedback_loop]||phase_mvt4_objective_override_near_invisibility[mvt4.m1_objective_excitement_soft_capture_refine,mvt4.m2_terminal_and_frontier_guard_coherence,mvt4.m3_phase_policy_cap_for_hardcoded_channel]||phase_mvt5_validation_rollout_and_freeze[mvt5.m1_batch_validation_matrix,mvt5.m2_canonical_report_and_gate_update,mvt5.m3_freeze_and_regression_guard]", "completed_micro_total": 18, "completed_phase_count": 6, "active_target": null, "base_promotion_target": 0.62, "target_adapt_enable": 0, "target_adapt_rate": 0.08, "promotion_target_hard_max": 0.9, "early_target_cap_enable": 1, "early_target_cap": 0.58, "early_target_cap_phase_count": 1, "early_target_cap_micro_max": 3, "weight_rebase_enable": 1, "weight_rebase_alpha": 0.68, "weight_rebase_objective_boost": 0.3, "warmup_target_dampener_enable": 1, "warmup_target_dampener_observations": 96, "warmup_target_dampener_max_reduction": 0.14, "target_raise_only_when_score_ready": 1, "target_freeze_after_observation_gate": 1, "target_deficit_relief_rate": 0.0, "target_deficit_margin": 0.015, "adaptive_weights": {"train": 0.149, "integrate": 0.2286, "stability": 0.0788, "transfer": 0.2402, "safety": 0.0606, "introspection": 0.2428}, "phases": [{"phase_id": "phase_mvt0_instrumentation_and_gate_reliability", "label": "Phase MVT0 - Instrumentation and Gate Reliability", "enabled": 1, "completed": 1, "micro_index": 2, "current_stage_id": "mvt0.m3_reasoning_conf_signal_enable", "current_stage_label": "MVT0.3 Reasoning confidence signal enable", "current_stage_impact_rank": 0, "current_stage_impact_label": "", "current_stage_env_type_group": "", "current_stage_env_key_count": 0, "current_stage_ownership_action": "", "current_stage_execution_system": "", "current_stage_env_prefixes": [], "observations": 84, "score_ema": 0.622, "promotion_target": 0.62, "early_target_cap_applied": 1, "effective_min_observations": 84, "safety_floor": 0.42, "stability_floor": 0.4, "transfer_floor": 0.18, "promotion_blocked_reason": "init", "last_autostep_enabled": 1, "promotion_gate_ready": 1, "promotion_gate_met": 1, "train_ema": 0.6754, "integrate_ema": 0.6427, "stability_ema": 0.6019, "transfer_ema": 0.5497, "safety_ema": 0.7779, "introspection_ema": 0.543}, {"phase_id": "phase_mvt1_mv_to_learned_routing_bias_lift", "label": "Phase MVT1 - MV to Learned Routing Bias Lift", "enabled": 1, "completed": 1, "micro_index": 2, "current_stage_id": "mvt1.m3_objective_evidence_quality_gate", "current_stage_label": "MVT1.3 Objective evidence quality gate", "current_stage_impact_rank": 0, "current_stage_impact_label": "", "current_stage_env_type_group": "", "current_stage_env_key_count": 0, "current_stage_ownership_action": "", "current_stage_execution_system": "", "current_stage_env_prefixes": [], "observations": 100, "score_ema": 0.6815, "promotion_target": 0.62, "early_target_cap_applied": 0, "effective_min_observations": 100, "safety_floor": 0.42, "stability_floor": 0.4, "transfer_floor": 0.18, "promotion_blocked_reason": "init", "last_autostep_enabled": 1, "promotion_gate_ready": 1, "promotion_gate_met": 1, "train_ema": 0.7321, "integrate_ema": 0.7505, "stability_ema": 0.7307, "transfer_ema": 0.6291, "safety_ema": 0.8125, "introspection_ema": 0.5551}, {"phase_id": "phase_mvt2_intervention_rate_compression_soft_first", "label": "Phase MVT2 - Intervention Rate Compression (Soft-First)", "enabled": 1, "completed": 1, "micro_index": 2, "current_stage_id": "mvt2.m3_unresolved_context_override_guard", "current_stage_label": "MVT2.3 Unresolved-context override guard", "current_stage_impact_rank": 0, "current_stage_impact_label": "", "current_stage_env_type_group": "", "current_stage_env_key_count": 0, "current_stage_ownership_action": "", "current_stage_execution_system": "", "current_stage_env_prefixes": [], "observations": 116, "score_ema": 0.7142, "promotion_target": 0.62, "early_target_cap_applied": 0, "effective_min_observations": 116, "safety_floor": 0.42, "stability_floor": 0.4, "transfer_floor": 0.18, "promotion_blocked_reason": "init", "last_autostep_enabled": 1, "promotion_gate_ready": 1, "promotion_gate_met": 1, "train_ema": 0.7472, "integrate_ema": 0.7938, "stability_ema": 0.7612, "transfer_ema": 0.6293, "safety_ema": 0.8633, "introspection_ema": 0.5622}, {"phase_id": "phase_mvt3_memory_driven_learned_selection_lift", "label": "Phase MVT3 - Memory-Driven Learned Selection Lift", "enabled": 1, "completed": 1, "micro_index": 2, "current_stage_id": "mvt3.m3_pattern_uncertainty_feedback_loop", "current_stage_label": "MVT3.3 Pattern uncertainty feedback loop", "current_stage_impact_rank": 0, "current_stage_impact_label": "", "current_stage_env_type_group": "", "current_stage_env_key_count": 0, "current_stage_ownership_action": "", "current_stage_execution_system": "", "current_stage_env_prefixes": [], "observations": 124, "score_ema": 0.6984, "promotion_target": 0.62, "early_target_cap_applied": 0, "effective_min_observations": 124, "safety_floor": 0.42, "stability_floor": 0.4, "transfer_floor": 0.18, "promotion_blocked_reason": "init", "last_autostep_enabled": 1, "promotion_gate_ready": 1, "promotion_gate_met": 1, "train_ema": 0.7072, "integrate_ema": 0.7, "stability_ema": 0.659, "transfer_ema": 0.7309, "safety_ema": 0.8429, "introspection_ema": 0.5383}, {"phase_id": "phase_mvt4_objective_override_near_invisibility", "label": "Phase MVT4 - Objective Override Near-Invisibility", "enabled": 1, "completed": 1, "micro_index": 2, "current_stage_id": "mvt4.m3_phase_policy_cap_for_hardcoded_channel", "current_stage_label": "MVT4.3 Phase policy cap for hardcoded channel", "current_stage_impact_rank": 0, "current_stage_impact_label": "", "current_stage_env_type_group": "", "current_stage_env_key_count": 0, "current_stage_ownership_action": "", "current_stage_execution_system": "", "current_stage_env_prefixes": [], "observations": 134, "score_ema": 0.7281, "promotion_target": 0.62, "early_target_cap_applied": 0, "effective_min_observations": 134, "safety_floor": 0.42, "stability_floor": 0.4, "transfer_floor": 0.18, "promotion_blocked_reason": "init", "last_autostep_enabled": 1, "promotion_gate_ready": 1, "promotion_gate_met": 1, "train_ema": 0.7796, "integrate_ema": 0.7682, "stability_ema": 0.7576, "transfer_ema": 0.7209, "safety_ema": 0.8158, "introspection_ema": 0.5712}, {"phase_id": "phase_mvt5_validation_rollout_and_freeze", "label": "Phase MVT5 - Validation, Rollout, and Freeze", "enabled": 1, "completed": 1, "micro_index": 2, "current_stage_id": "mvt5.m3_freeze_and_regression_guard", "current_stage_label": "MVT5.3 Freeze and regression guard", "current_stage_impact_rank": 0, "current_stage_impact_label": "", "current_stage_env_type_group": "", "current_stage_env_key_count": 0, "current_stage_ownership_action": "", "current_stage_execution_system": "", "current_stage_env_prefixes": [], "observations": 0, "score_ema": 0.512, "promotion_target": 0.62, "early_target_cap_applied": 0, "effective_min_observations": 152, "safety_floor": 0.42, "stability_floor": 0.4, "transfer_floor": 0.18, "promotion_blocked_reason": "init", "last_autostep_enabled": 1, "promotion_gate_ready": 0, "promotion_gate_met": 0, "train_ema": 0.5221, "integrate_ema": 0.5622, "stability_ema": 0.6519, "transfer_ema": 0.4411, "safety_ema": 0.7508, "introspection_ema": 0.4235}]}, "micro_progress_persisted_series_value": 48.6, "micro_progress_batch_quality_ema": 1.0, "micro_progress_regression_fail_streak": 1, "pane_sash_x": 619}